Metadata-Version: 2.1
Name: hello-world-jitregiydo
Version: 0.0.1
Summary: my name is neo
Home-page: https://github.com/ericjaychi/sample-pypi-package
Author: Neo Matrix
Author-email: agentsmitt@gmail.com
License: UNKNOWN
Platform: UNKNOWN
Classifier: Programming Language :: Python :: 3.8
Classifier: License :: OSI Approved :: MIT License
Classifier: Operating System :: OS Independent
Requires-Python: >=3.6
